prospecpy/__init__.py
prospecpy/anchor_points.py
prospecpy/baseline.py
prospecpy/cut_range.py
prospecpy/interact.py
prospecpy/io.py
prospecpy/peak_fit.py
prospecpy/prospecpy.py
prospecpy/remove_wv.py
prospecpy/second_deriv.py
prospecpy/vaporfit.py
prospecpy/version.py
prospecpy-0.1.0.dist-info/METADATA
prospecpy-0.1.0.dist-info/WHEEL
prospecpy-0.1.0.dist-info/licenses/LICENSE
prospecpy-0.1.0.dist-info/RECORD
