Metadata-Version: 2.4
Name: prospecpy
Version: 0.1.0
Summary: Python package for analyzing FTIR Spectroscopy Data from Bruker instruments.
Project-URL: Homepage, https://github.com/uw-ssec/ProSpecPy
Project-URL: Repository, https://github.com/uw-ssec/ProSpecPy.git
Project-URL: Issues, https://github.com/uw-ssec/ProSpecPy/issues
License: BSD 3-Clause License
License-File: LICENSE
Classifier: Development Status :: 3 - Alpha
Classifier: Intended Audience :: Developers
Classifier: License :: OSI Approved :: BSD License
Classifier: Operating System :: OS Independent
Classifier: Programming Language :: Python :: 3.11
Classifier: Programming Language :: Python :: 3.12
Classifier: Topic :: Scientific/Engineering
Classifier: Topic :: Software Development :: Build Tools
Classifier: Topic :: Software Development :: Libraries :: Python Modules
Requires-Python: >=3.11
Requires-Dist: brukeropusreader
Requires-Dist: matplotlib
Requires-Dist: numpy
Requires-Dist: openpyxl
Requires-Dist: pandas
Requires-Dist: scipy
Requires-Dist: tabulate
Provides-Extra: all
Requires-Dist: jupyter-book; extra == 'all'
Requires-Dist: nox; extra == 'all'
Requires-Dist: numpydoc; extra == 'all'
Requires-Dist: pre-commit; extra == 'all'
Requires-Dist: pytest-cov; extra == 'all'
Requires-Dist: pytest-mock; extra == 'all'
Requires-Dist: pytest-xdist; extra == 'all'
Requires-Dist: pytest>=6; extra == 'all'
Requires-Dist: sphinx-automodapi; extra == 'all'
Requires-Dist: sphinx-panels; extra == 'all'
Requires-Dist: sphinx-rtd-theme; extra == 'all'
Requires-Dist: sphinxcontrib-mermaid; extra == 'all'
Provides-Extra: dev
Requires-Dist: nox; extra == 'dev'
Requires-Dist: pre-commit; extra == 'dev'
Requires-Dist: pytest-cov; extra == 'dev'
Requires-Dist: pytest-mock; extra == 'dev'
Requires-Dist: pytest-xdist; extra == 'dev'
Requires-Dist: pytest>=6; extra == 'dev'
Provides-Extra: docs
Requires-Dist: jupyter-book; extra == 'docs'
Requires-Dist: numpydoc; extra == 'docs'
Requires-Dist: sphinx-automodapi; extra == 'docs'
Requires-Dist: sphinx-panels; extra == 'docs'
Requires-Dist: sphinx-rtd-theme; extra == 'docs'
Requires-Dist: sphinxcontrib-mermaid; extra == 'docs'
